Metadata-Version: 2.1
Name: maigret
Version: 0.4.4
Summary: Collect a dossier on a person by username from a huge number of sites
Home-page: https://github.com/soxoj/maigret
Author: Soxoj
Author-email: soxoj@protonmail.com
License: MIT
License-File: LICENSE
